Metadata-Version: 1.1
Name: opat
Version: 0.0.5.2
Summary: opat is a Python library for evaluatoin of financial portfolios
Home-page: https://github.com/shawnlinxl/opat
Author: Shawn Lin
Author-email: shawnlin.xl@gmail.com
License: Apache License, Version 2.0
Platform: UNKNOWN
Classifier: Development Status :: 1 - Planning
Classifier: Programming Language :: Python
Classifier: Programming Language :: Python :: 3
Classifier: Programming Language :: Python :: 3.7
Classifier: License :: OSI Approved :: Apache Software License
Classifier: Intended Audience :: Science/Research
Classifier: Topic :: Scientific/Engineering
Classifier: Topic :: Scientific/Engineering :: Mathematics
Classifier: Operating System :: OS Independent
